rotu/__init__.py
rotu/main.py
rotu/assets/basics.css
rotu/assets/layout.css
rotu/assets/object.css
rotu/assets/fonts/Lora-Bold.woff2
rotu/assets/fonts/Lora-Regular.woff2
rotu/assets/fonts/OpenSans-Bold.woff2
rotu/assets/fonts/OpenSans-BoldItalic.woff2
rotu/assets/fonts/OpenSans-ExtraBold.woff2
rotu/assets/fonts/OpenSans-ExtraBoldItalic.woff2
rotu/assets/fonts/OpenSans-Italic.woff2
rotu/assets/fonts/OpenSans-Light.woff2
rotu/assets/fonts/OpenSans-LightItalic.woff2
rotu/assets/fonts/OpenSans-Regular.woff2
rotu/assets/fonts/OpenSans-SemiBold.woff2
rotu/assets/fonts/OpenSans-SemiBoldItalic.woff2
rotu/assets/styles/style_01.css
rotu/assets/styles/style_02.css
rotu/assets/styles/style_03.css
rotu/scenes/00/0.scene.toml
rotu/scenes/00/a.scene.toml
rotu/scenes/01/a.scene.toml
rotu/scenes/02/a.scene.toml
rotu/scenes/24/a.scene.toml
rotu/test/__init__.py
rotu/test/test_goals.py
rotu-0.6.0.dist-info/METADATA
rotu-0.6.0.dist-info/WHEEL
rotu-0.6.0.dist-info/entry_points.txt
rotu-0.6.0.dist-info/licenses/COPYING
rotu-0.6.0.dist-info/RECORD
