Metadata-Version: 2.1
Name: rotu
Version: 0.6.0
Summary: A work of Interactive Fiction.
Author-email: D E Haynes <tundish@gigeconomy.org.uk>
Maintainer-email: Tundish <tundish@gigeconomy.org.uk>
License:                     GNU AFFERO GENERAL PUBLIC LICENSE
License-File: COPYING
Keywords: game jam,interactive fiction
Classifier: Development Status :: 4 - Beta
Classifier: Programming Language :: Python
Requires-Python: >=3.11
Requires-Dist: balladeer>=0.48.0
Provides-Extra: blog
Requires-Dist: pelican-neighbors; extra == 'blog'
Requires-Dist: pelican-readtime; extra == 'blog'
Requires-Dist: pelican[markdown]; extra == 'blog'
